README.rst
setup.cfg
setup.py
Preflyt.egg-info/PKG-INFO
Preflyt.egg-info/SOURCES.txt
Preflyt.egg-info/dependency_links.txt
Preflyt.egg-info/requires.txt
Preflyt.egg-info/top_level.txt
Preflyt.egg-info/zip-safe
preflyt/__init__.py
preflyt/base.py
preflyt/utils.py
preflyt.egg-info/SOURCES.txt
preflyt/checkers/__init__.py
preflyt/checkers/elasticsearch.py
preflyt/checkers/environment.py
preflyt/checkers/filesystem.py
preflyt/checkers/postgres.py
preflyt/checkers/sqlite.py
preflyt/checkers/webservice.py