Metadata-Version: 1.1
Name: preflyt
Version: 0.4.0
Summary: A simple system state test utility
Home-page: https://github.com/humangeo/preflyt
Author: Aru Sahni
Author-email: aru@thehumangeo.com
License: MIT
Keywords: runtime test test system environment check checker
Platform: UNKNOWN
Classifier: Development Status :: 4 - Beta
Classifier: Environment :: Plugins
Classifier: Intended Audience :: Developers
Classifier: License :: OSI Approved :: MIT License
Classifier: Programming Language :: Python :: 3 :: Only
Classifier: Topic :: System :: Monitoring
Classifier: Topic :: Software Development :: Testing
